seriallll/__init__.py
seriallll/py.typed
seriallll-0.1.3.dist-info/METADATA
seriallll-0.1.3.dist-info/WHEEL
seriallll-0.1.3.dist-info/RECORD
