Metadata-Version: 2.4
Name: seriallll
Version: 0.1.3
Summary: Add your description here
Author-email: Kirill Semenov <cyrillsphoto@gmail.com>
Requires-Python: >=3.8
Requires-Dist: pyserial>=3.5
